pyliteadmin/__init__.py
pyliteadmin/app.py
pyliteadmin/db.py
pyliteadmin/pyliteadmin.css
pyliteadmin-1.0.1.dist-info/LICENSE
pyliteadmin-1.0.1.dist-info/METADATA
pyliteadmin-1.0.1.dist-info/WHEEL
pyliteadmin-1.0.1.dist-info/entry_points.txt
pyliteadmin-1.0.1.dist-info/top_level.txt
pyliteadmin-1.0.1.dist-info/RECORD
