Metadata-Version: 2.1
Name: pyliteadmin
Version: 1.0.1
Summary: A TUI for CRUDing sqlite databases.
Author-email: Brandon Demelo <brandon@brandondemelo.com>
Project-URL: Homepage, https://github.com/The-Bush/pyliteadmin
Project-URL: Bug Tracker, https://github.com/The-Bush/pyliteadmin/issues
Classifier: Programming Language :: Python :: 3
Classifier: License :: OSI Approved :: MIT License
Classifier: Operating System :: OS Independent
Requires-Python: >=3.7
License-File: LICENSE
Requires-Dist: textual
